mmdf/__init__.py
mmdf/_gemmi_utils.py
mmdf/_pdb_utils.py
mmdf/functions.py
mmdf/py.typed
mmdf-0.0.5.dist-info/METADATA
mmdf-0.0.5.dist-info/WHEEL
mmdf-0.0.5.dist-info/licenses/LICENSE
mmdf-0.0.5.dist-info/RECORD
